raisetool/__init__.py
raisetool/formatter.py
raisetool-1.0.0.dist-info/LICENSE
raisetool-1.0.0.dist-info/METADATA
raisetool-1.0.0.dist-info/WHEEL
raisetool-1.0.0.dist-info/RECORD
