Metadata-Version: 2.1
Name: raisetool
Version: 1.0.0
Summary: Rise class for formatting thrown exception messages.
Home-page: https://github.com/Szumak75/RaiseTool
License: MIT
Author: Jacek Kotlarski
Author-email: szumak@virthost.pl
Requires-Python: >=3.7,<4.0
Classifier: License :: OSI Approved :: MIT License
Classifier: Programming Language :: Python :: 3
Classifier: Programming Language :: Python :: 3.7
Classifier: Programming Language :: Python :: 3.8
Classifier: Programming Language :: Python :: 3.9
Classifier: Programming Language :: Python :: 3.10
Classifier: Programming Language :: Python :: 3.11
Classifier: Programming Language :: Python :: 3
Classifier: Topic :: Software Development :: Libraries
Requires-Dist: attribtool (>=1,<2)
Project-URL: Repository, https://github.com/Szumak75/RaiseTool
